{
  "p1": {
    "name": "Setup quote + voci miste",
    "started": "2026-05-25T22:32:17.891Z",
    "steps": [
      {
        "name": "cleanup quote AGENT-R-%",
        "ok": true,
        "detail": "nessun residuo"
      },
      {
        "name": "cleanup supplier_availability su date di test",
        "ok": true,
        "detail": "2027-08-15,2027-09-20,2027-10-10,2027-11-22"
      },
      {
        "name": "quote creato via UI",
        "ok": true,
        "detail": "f080797f-47cb-462e-9aea-17fba76b2b5e"
      },
      {
        "name": "header completato via DB",
        "ok": true,
        "detail": null
      },
      {
        "name": "8 voci inserite",
        "ok": true,
        "detail": "8/8"
      },
      {
        "name": "total_cost ok",
        "ok": true,
        "detail": "€19680"
      },
      {
        "name": "total_client ok (25% markup)",
        "ok": true,
        "detail": "€24600"
      }
    ],
    "screenshots": [
      "p1-01-login.png",
      "p1-02-quotes-list.png",
      "p1-03-quote-created.png"
    ],
    "bugs": [],
    "finished": "2026-05-25T22:32:28.061Z",
    "ok": true,
    "durationSec": 10.17
  },
  "p2": {
    "name": "Calcoli automatici",
    "started": "2026-05-25T22:32:28.061Z",
    "steps": [
      {
        "name": "PER_GUEST ricalcolato a 150",
        "ok": true,
        "detail": "[150,150,150]"
      },
      {
        "name": "PER_TABLE ricalcolato a 15",
        "ok": true,
        "detail": "[15]"
      },
      {
        "name": "markup default 25→18 propagato a tutte le voci",
        "ok": true,
        "detail": null
      },
      {
        "name": "Override markup 50% applicato solo a \"Menu cena\"",
        "ok": true,
        "detail": "€21375"
      },
      {
        "name": "Altre voci mantengono default 18% (no leak override)",
        "ok": true,
        "detail": null
      },
      {
        "name": "snapshot_price negativo rifiutato dal DB (check constraint)",
        "ok": true,
        "detail": "new row for relation \"quote_items\" violates check constraint \"quote_items_snapshot_price_check\""
      }
    ],
    "screenshots": [],
    "bugs": [],
    "finished": "2026-05-25T22:32:30.299Z",
    "ok": true,
    "durationSec": 2.238
  },
  "p3": {
    "name": "Quote items edge cases",
    "started": "2026-05-25T22:32:30.299Z",
    "steps": [
      {
        "name": "quantity=0 rifiutato (check quantity > 0)",
        "ok": true,
        "detail": "new row for relation \"quote_items\" violates check constraint \"quote_items_quantity_check\""
      },
      {
        "name": "quantity=999999 accettato",
        "ok": true,
        "detail": "line_cost=999999"
      },
      {
        "name": "voci duplicate accettate (atteso per UX)",
        "ok": true,
        "detail": null
      },
      {
        "name": "sort_order modificabile (riordino voci)",
        "ok": true,
        "detail": null
      },
      {
        "name": "basis FLAT→PER_GUEST con quantity auto-pop applicato (DB richiede quantity esplicita)",
        "ok": true,
        "detail": null
      },
      {
        "name": "quote vuoto ammesso (totals=0)",
        "ok": true,
        "detail": null
      }
    ],
    "screenshots": [],
    "bugs": [
      {
        "id": "AGENT-R-001",
        "severity": "LOW",
        "area": "validation.qty-max",
        "msg": "Nessun upper bound su quantity (999999 accettato). Suggerito guard a livello applicativo (no DB constraint).",
        "repro": null,
        "phase": "p3",
        "ts": "2026-05-25T22:32:30.415Z"
      },
      {
        "id": "AGENT-R-002",
        "severity": "MEDIUM",
        "area": "validation.empty-label",
        "msg": "name_snapshot='' accettato → UI mostrerà voce senza titolo. Aggiungi NOT EMPTY constraint o validation lato app.",
        "repro": null,
        "phase": "p3",
        "ts": "2026-05-25T22:32:30.536Z"
      }
    ],
    "finished": "2026-05-25T22:32:31.208Z",
    "ok": true,
    "durationSec": 0.909
  },
  "p4": {
    "name": "Supplier reassignment + RLS",
    "started": "2026-05-25T22:32:31.209Z",
    "steps": [
      {
        "name": "Voce \"AGENT-R Servizio Foto Full Day\" riassegnata a Fiori",
        "ok": true,
        "detail": null
      },
      {
        "name": "RLS: fornitore Foto NON vede più la voce riassegnata",
        "ok": true,
        "detail": null
      },
      {
        "name": "RLS: fornitore Fiori vede la voce riassegnata",
        "ok": true,
        "detail": "AGENT-R Servizio Foto Full Day"
      },
      {
        "name": "supplier_id → null (in-house WP) accettato",
        "ok": true,
        "detail": null
      },
      {
        "name": "RLS: dopo null, Fiori non vede più",
        "ok": true,
        "detail": null
      }
    ],
    "screenshots": [],
    "bugs": [],
    "finished": "2026-05-25T22:32:32.080Z",
    "ok": true,
    "durationSec": 0.871
  },
  "p5": {
    "name": "Status transitions",
    "started": "2026-05-25T22:32:32.081Z",
    "steps": [
      {
        "name": "quote-send invocato",
        "ok": true,
        "detail": "pdf_url=https://zfwlkvqxfzvubmfyxofs.supabase.co/storage/v1/object/s"
      },
      {
        "name": "status BOZZA→INVIATO",
        "ok": true,
        "detail": null
      },
      {
        "name": "access_token generato",
        "ok": true,
        "detail": "43f4202d"
      },
      {
        "name": "quote-accept-sign invocato",
        "ok": true,
        "detail": "{\"ok\":true,\"acceptance_id\":\"f4fad04b-3945-4200-9507-ff9a6263d942\",\"acceptance_pdf_url\":\"https://zfwlkvqxfzvubmfyxofs.sup"
      },
      {
        "name": "status INVIATO→ACCETTATO",
        "ok": true,
        "detail": "accepted_at=2026-05-25T22:32:35.048+00:00"
      },
      {
        "name": "Banner \"Preventivo accettato\" visibile",
        "ok": true,
        "detail": null
      },
      {
        "name": "Campi header in lock (isLocked) — 11 input disabled",
        "ok": true,
        "detail": null
      },
      {
        "name": "Bottone \"Genera contratto\" visibile",
        "ok": true,
        "detail": null
      },
      {
        "name": "Navigazione /contracts post-click",
        "ok": true,
        "detail": null
      },
      {
        "name": "status ACCETTATO→CONVERTITO_IN_CONTRATTO",
        "ok": true,
        "detail": null
      },
      {
        "name": "Contratto inserito (BOZZA, €32331.3)",
        "ok": true,
        "detail": "afd0630e-9467-4f5e-8da2-b05df38a8418"
      },
      {
        "name": "INVIATO→RIFIUTATO via token funziona",
        "ok": true,
        "detail": null
      }
    ],
    "screenshots": [
      "p5-01-quote-accepted-banner.png",
      "p5-02-after-generate-contract.png"
    ],
    "bugs": [
      {
        "id": "AGENT-R-003",
        "severity": "MEDIUM",
        "area": "status.transitions",
        "msg": "WP può tornare INVIATO→BOZZA senza vincoli DB. Le state-machine sono solo client-side (no DB trigger). Cliente potrebbe avere link \"scaduto\" senza saperlo.",
        "repro": "UPDATE quotes SET status='BOZZA' WHERE id='f080797f-47cb-462e-9aea-17fba76b2b5e' AND owner_id=auth.uid()",
        "phase": "p5",
        "ts": "2026-05-25T22:32:34.446Z"
      },
      {
        "id": "AGENT-R-004",
        "severity": "MEDIUM",
        "area": "status.transitions",
        "msg": "Transition ACCETTATO→RIFIUTATO consentita da DB (nessun trigger di validazione state-machine). Solo UI/RPC la limita.",
        "repro": null,
        "phase": "p5",
        "ts": "2026-05-25T22:32:46.910Z"
      }
    ],
    "finished": "2026-05-25T22:32:46.959Z",
    "ok": true,
    "durationSec": 14.878
  },
  "p6": {
    "name": "PDF generation",
    "started": "2026-05-25T22:32:46.960Z",
    "steps": [
      {
        "name": "PDF NEUTRA generato",
        "ok": true,
        "detail": "https://zfwlkvqxfzvubmfyxofs.supabase.co/storage/v1/object/sign/quote-pdfs/f0807"
      },
      {
        "name": "PDF NEUTRA scaricato",
        "ok": true,
        "detail": "18114 bytes"
      },
      {
        "name": "PDF PREMIUM generato (premium_applied=true)",
        "ok": true,
        "detail": "https://zfwlkvqxfzvubmfyxofs.supabase.co/storage/v1/object/sign/quote-pdfs/f0807"
      },
      {
        "name": "PDF PREMIUM scaricato",
        "ok": true,
        "detail": "18193 bytes"
      },
      {
        "name": "PDF i18n+simboli generato",
        "ok": true,
        "detail": "https://zfwlkvqxfzvubmfyxofs.supabase.co/storage/v1/object/s"
      },
      {
        "name": "PDF 55 voci generato (paginazione)",
        "ok": true,
        "detail": "https://zfwlkvqxfzvubmfyxofs.supabase.co/storage/v1/object/s"
      },
      {
        "name": "PDF 55 voci scaricato",
        "ok": true,
        "detail": "43956 bytes"
      }
    ],
    "screenshots": [],
    "bugs": [],
    "finished": "2026-05-25T22:32:51.076Z",
    "ok": true,
    "durationSec": 4.116
  },
  "p7": {
    "name": "Send + accept (token public route)",
    "started": "2026-05-25T22:32:51.077Z",
    "steps": [
      {
        "name": "quote-send eseguito su q3",
        "ok": true,
        "detail": "8051e0e8"
      },
      {
        "name": "access_token presente",
        "ok": true,
        "detail": null
      },
      {
        "name": "sent_email_log popolato (1 entry)",
        "ok": true,
        "detail": null
      },
      {
        "name": "Public preview mostra titolo quote",
        "ok": true,
        "detail": null
      }
    ],
    "screenshots": [
      "p7-01-public-preview.png"
    ],
    "bugs": [],
    "finished": "2026-05-25T22:32:54.824Z",
    "ok": true,
    "durationSec": 3.747
  },
  "p8": {
    "name": "Revisioni + forza unlock",
    "started": "2026-05-25T22:32:54.824Z",
    "steps": [
      {
        "name": "q4 portato ad ACCETTATO",
        "ok": true,
        "detail": null
      },
      {
        "name": "revision incrementato a 2",
        "ok": true,
        "detail": null
      },
      {
        "name": "modifica salvata su quote ACCETTATO",
        "ok": true,
        "detail": null
      },
      {
        "name": "sent_email_log preservato dopo modifica",
        "ok": true,
        "detail": "0 entry"
      }
    ],
    "screenshots": [],
    "bugs": [],
    "finished": "2026-05-25T22:32:55.137Z",
    "ok": true,
    "durationSec": 0.313
  },
  "p9": {
    "name": "Cleanup AGENT-R-%",
    "started": "2026-05-25T22:32:55.137Z",
    "steps": [
      {
        "name": "cleanup 1 quote AGENT-R%",
        "ok": true,
        "detail": null
      },
      {
        "name": "cleanup 1 contract AGENT-R%",
        "ok": true,
        "detail": null
      }
    ],
    "screenshots": [],
    "bugs": [],
    "finished": "2026-05-25T22:32:55.355Z",
    "ok": true,
    "durationSec": 0.218
  }
}